{
  "$schema": "https://biomejs.dev/schemas/1.9.4/schema.json",
  "vcs": {
    "enabled": false,
    "clientKind": "git",
    "useIgnoreFile": false
  },
  "files": {
    "ignoreUnknown": false,
    "ignore": ["node_modules/**", "dist/**"]
  },
  "formatter": {
    "enabled": true,
    "formatWithErrors": false,
    "ignore": [],
    "attributePosition": "auto",
    "indentStyle": "space",
    "indentWidth": 2,
    "lineWidth": 100
  },
  "organizeImports": {
    "enabled": true
  },
  "linter": {
    "enabled": true,
    "rules": {
      "recommended": true,
      "suspicious": {
        "noExplicitAny": "error"
      },
      "style": {
        "useTemplate": "error"
      },
      "correctness": {
        "noUnusedImports": "warn",
        "noUnusedLabels": "warn",
        "noUnusedVariables": "warn",
        "noUnusedFunctionParameters": "warn"
      }
    }
  },
  "javascript": {
    "formatter": {
      "arrowParentheses": "asNeeded",
      "bracketSameLine": false,
      "bracketSpacing": true,
      "jsxQuoteStyle": "double",
      "quoteProperties": "asNeeded",
      "quoteStyle": "single",
      "semicolons": "asNeeded",
      "trailingCommas": "none"
    }
  },
  "json": {
    "parser": {
      "allowComments": true
    },
    "formatter": {
      "trailingCommas": "none",
      "indentStyle": "space",
      "indentWidth": 2
    }
  }
}
